exifmapper/__init__.py
exifmapper/gui.py
exifmapper/resources/icon.png
exifmapper-1.0.1.dist-info/licenses/LICENSE
exifmapper-1.0.1.dist-info/METADATA
exifmapper-1.0.1.dist-info/WHEEL
exifmapper-1.0.1.dist-info/entry_points.txt
exifmapper-1.0.1.dist-info/top_level.txt
exifmapper-1.0.1.dist-info/RECORD
