Metadata-Version: 2.4
Name: exifmapper
Version: 1.0.1
Summary: A desktop application to extract GPS coordinates from images and display them on an interactive map
Home-page: https://github.com/SirCryptic/exifmapper
Author: SirCryptic
Author-email: sircryptic@protonmail.com
License: MIT
Classifier: Programming Language :: Python :: 3
Classifier: License :: OSI Approved :: MIT License
Classifier: Operating System :: Microsoft :: Windows
Classifier: Operating System :: POSIX :: Linux
Requires-Python: >=3.11
License-File: LICENSE
Requires-Dist: PyQt6>=6.7.0
Requires-Dist: requests>=2.31.0
Requires-Dist: Pillow>=10.2.0
Requires-Dist: folium>=0.15.0
Requires-Dist: geopy>=2.4.0
Requires-Dist: simplekml>=1.3.6
Dynamic: author
Dynamic: author-email
Dynamic: classifier
Dynamic: description
Dynamic: description-content-type
Dynamic: home-page
Dynamic: license
Dynamic: license-file
Dynamic: requires-dist
Dynamic: requires-python
Dynamic: summary
